pyavro_gen/__init__.py
pyavro_gen/enum_with_schema_provider.py
pyavro_gen/equality_test.py
pyavro_gen/generation_classes.py
pyavro_gen/generator.py
pyavro_gen/pyavrogen.py
pyavro_gen/schema_and_classes_container.py
pyavro_gen/tests.py
pyavro_gen/codewriters/__init__.py
pyavro_gen/codewriters/containers.py
pyavro_gen/codewriters/core.py
pyavro_gen/codewriters/extended.py
pyavro_gen/codewriters/logicaltypes.py
pyavro_gen/codewriters/namespace.py
pyavro_gen/codewriters/utils.py
pyavro_gen/modules/__init__.py
pyavro_gen/modules/avsc_schema_dependency_checker.py
pyavro_gen/modules/fields_collector.py
pyavro_gen-0.3.4.data/scripts/pyavrogen.py
pyavro_gen-0.3.4.dist-info/COPYING
pyavro_gen-0.3.4.dist-info/METADATA
pyavro_gen-0.3.4.dist-info/WHEEL
pyavro_gen-0.3.4.dist-info/top_level.txt
pyavro_gen-0.3.4.dist-info/RECORD
