Metadata-Version: 2.1
Name: pyavro-gen
Version: 0.3.4
Summary: A typed class generator for Avro Schemata
Home-page: https://gitlab.com/Jaumo/pyavro-gen
Author: Jaumo GmbH
Author-email: nicola.bova@jaumo.com
License: Apache2
Keywords: avro,classes,typing,types,type,typed,generation,creation,schema,schemas,schemata
License-File: COPYING
Requires-Dist: networkx>=2.8.7
Requires-Dist: pygments>=2.13.0
Requires-Dist: factory-boy>=3.2.1
Requires-Dist: undictify>=0.11.3
Requires-Dist: faker>=15.1.1
Requires-Dist: isort>=5.10.1
Requires-Dist: avro-preprocessor>=0.1.12
Requires-Dist: pytz>=2022.5
Requires-Dist: dataclasses-avroschema>=0.37.1
